fontio.py
terminalio.py
adafruit_blinka_displayio-2.3.0.dist-info/licenses/LICENSE
bitmaptools/__init__.py
busdisplay/__init__.py
busdisplay/_displaybus.py
displayio/__init__.py
displayio/_area.py
displayio/_bitmap.py
displayio/_colorconverter.py
displayio/_colorspace.py
displayio/_constants.py
displayio/_displaycore.py
displayio/_group.py
displayio/_helpers.py
displayio/_ondiskbitmap.py
displayio/_palette.py
displayio/_structs.py
displayio/_tilegrid.py
displayio/resources/__init__.py
displayio/resources/ter-u12n.bdf
displayio/resources/ter-u12n.bdf.license
epaperdisplay/__init__.py
fourwire/__init__.py
i2cdisplaybus/__init__.py
paralleldisplaybus/__init__.py
vectorio/__init__.py
vectorio/_circle.py
vectorio/_polygon.py
vectorio/_rectangle.py
vectorio/_vectorshape.py
adafruit_blinka_displayio-2.3.0.dist-info/METADATA
adafruit_blinka_displayio-2.3.0.dist-info/WHEEL
adafruit_blinka_displayio-2.3.0.dist-info/top_level.txt
adafruit_blinka_displayio-2.3.0.dist-info/RECORD
