Metadata-Version: 2.4
Name: adafruit-blinka-displayio
Version: 2.3.0
Summary: displayio for Blinka
Author-email: Adafruit Industries <circuitpython@adafruit.com>
License: MIT
Project-URL: Homepage, https://github.com/adafruit/Adafruit_Blinka_Displayio.git
Keywords: adafruit,blinka,circuitpython,micropython,displayio,lcd,tft,display,pitft
Classifier: Intended Audience :: Developers
Classifier: Topic :: Software Development :: Libraries
Classifier: Topic :: Software Development :: Embedded Systems
Classifier: Topic :: System :: Hardware
Classifier: License :: OSI Approved :: MIT License
Classifier: Programming Language :: Python :: 3
License-File: LICENSE
Requires-Dist: Adafruit-Blinka>=7.0.0
Requires-Dist: adafruit-circuitpython-typing
Requires-Dist: adafruit-circuitpython-bitmap-font
Dynamic: license-file
